{
     "fluids":[
        {
            "name":"Neodymium Sulfate Aq",
            "textureName": "liquidAqNeodymiumSulfate",
            "temperature": 320,
	    "material": "water",
            "density": 1300,
            "viscosity": 2000,            
            "lightLevel": 1.0,
            "isGas": false,
            "flowLength": 5,
            "bucket": {
                "textureName": "bucket_AqNeodymiumSulfate"
            }
        },
        {
            "name":"Sodium Chromate aq",
            "textureName": "liquidAqSodiumChromate",
            "temperature": 320,
	    "material": "water",
            "density": 1300,
            "viscosity": 2000,            
            "lightLevel": 1.0,
            "isGas": false,
            "flowLength": 5,
            "bucket": {
                "textureName": "bucket_AqSodiumChromate"
            }
        },
        {
            "name":"Titanium TetraChloride",
            "textureName": "liquidTitaniumTetraChloride",
            "temperature": 300,
	    "material": "water",
            "density": 1726,
            "viscosity": 3000,            
            "lightLevel": 1.0,
            "isGas": false,
            "flowLength": 5,
            "bucket": {
                "textureName": "bucket_AqSodiumChromate"
            }
        },
        {
            "name":"Liquid Bismuth",
            "textureName": "liquidBismuth",
            "temperature": 570,
	    "material": "lava",
            "density": 2000,
            "viscosity": 9000,            
            "lightLevel": 1.0,
            "isGas": false,
            "flowLength": 2,
            "bucket": {
                "textureName": "bucket_bismuth"
            }
        },
        {
            "name":"Liquid Bismuth Bronze",
            "textureName": "liquidBismuthBronze",
            "temperature": 1285,
            "luminosity": 8,
	    "material": "lava",
            "density": 3000,
            "viscosity": 8000,            
            "lightLevel": 1.0,
            "isGas": false,
            "flowLength": 2,
            "bucket": {
                "textureName": "bucket_bismuth_bronze"
            }
        },
        {
            "name":"Liquid Black Bronze",
            "textureName": "liquidBlackBronze",
            "temperature": 1370,
            "luminosity": 9,
	    "material": "lava",
            "density": 3000,
            "viscosity": 7000,            
            "lightLevel": 1.0,
            "isGas": false,
            "flowLength": 2,
            "bucket": {
                "textureName": "bucket_black_bronze"
            }
        },
        {
            "name":"Liquid Sterling Silver",
            "textureName": "liquidSterlingSilver",
            "temperature": 1200,
            "luminosity": 8,
	    "material": "lava",
            "density": 3500,
            "viscosity": 8000,            
            "lightLevel": 1.0,
            "isGas": false,
            "flowLength": 2,
            "bucket": {
                "textureName": "bucket_sterling_silver"
            }
        },
        {
            "name":"Liquid Rose Gold",
            "textureName": "liquidRoseGold",
            "temperature": 1260,
            "luminosity": 8,
	    "material": "lava",
            "density": 4000,
            "viscosity": 8000,            
            "lightLevel": 1.0,
            "isGas": false,
            "flowLength": 2,
            "bucket": {
                "textureName": "bucket_rose_gold"
            }
        },
        {
            "name":"Liquid Permalloy",
            "textureName": "liquidPermalloy",
            "temperature": 1750,
            "luminosity": 11,
	    "material": "lava",
            "density": 8000,
            "viscosity": 6000,            
            "lightLevel": 1.0,
            "isGas": false,
            "flowLength": 3,
            "bucket": {
                "textureName": "bucket_permalloy"
            }
        },
        {
            "name":"Liquid Mangalloy",
            "textureName": "liquidMangalloy",
            "temperature": 1740,
            "luminosity": 11,
	    "material": "lava",
            "density": 7000,
            "viscosity": 6000,            
            "lightLevel": 1.0,
            "isGas": false,
            "flowLength": 3,
            "bucket": {
                "textureName": "bucket_permalloy"
            }
        },
        {
            "name":"Liquid Iridium",
            "textureName": "liquidIridium",
            "temperature": 2466,
            "luminosity": 11,
	    "material": "lava",
            "density": 22000,
            "viscosity": 8000,            
            "lightLevel": 1.0,
            "isGas": false,
            "flowLength": 3,
            "bucket": {
                "textureName": "bucket_sterling_silver"
            }
        },
        {
            "name":"Liquid Cadmium",
            "textureName": "liquidCadmium",
            "temperature": 600,
            "luminosity": 1,
	    "material": "lava",
            "density": 8600,
            "viscosity": 8000,            
            "lightLevel": 1.0,
            "isGas": false,
            "flowLength": 3,
            "bucket": {
                "textureName": "bucket_bismuth_bronze"
            }
        },
        {
            "name":"Liquid Quartz Glass",
            "textureName": "liquidQuartzGlass",
            "temperature": 1990,
            "luminosity": 12,
	    "material": "lava",
            "density": 2300,
            "viscosity": 9000,            
            "lightLevel": 1.0,
            "isGas": false,
            "flowLength": 3,
            "bucket": {
                "textureName": "bucket_quartz_glass"
            }
        },
        {
            "name":"Liquid Black Quartz Glass",
            "textureName": "liquidBlackQuartzGlass",
            "temperature": 1980,
            "luminosity": 11,
	    "material": "lava",
            "density": 2300,
            "viscosity": 9000,            
            "lightLevel": 1.0,
            "isGas": false,
            "flowLength": 3,
            "bucket": {
                "textureName": "bucket_quartz_glass"
            }
        },
        {
            "name":"molten.Silicon",
            "textureName": "liquidSilicon",
            "temperature": 1687,
            "luminosity": 9,
	    "material": "lava",
            "density": 2330,
            "viscosity": 7000,            
            "lightLevel": 1.0,
            "isGas": false,
            "flowLength": 3,
            "bucket": {
                "textureName": "bucket_quartz_glass"
            }
        },
        {
            "name":"Molten Sodium",
            "textureName": "molten.Sodium",
            "temperature": 98,
            "luminosity": 1,
	    "material": "lava",
            "density": 980,
            "viscosity": 9000,            
            "lightLevel": 1.0,
            "isGas": false,
            "flowLength": 3,
            "bucket": {
                "textureName": "bucket_quartz_glass"
            }
        },
        {
            "name":"Molten Plastic",
            "textureName": "liquidPlastic",
            "temperature": 200,
            "luminosity": 1,
	    "material": "lava",
            "density": 970,
            "viscosity": 9000,            
            "lightLevel": 1.0,
            "isGas": false,
            "flowLength": 3,
            "bucket": {
                "textureName": "bucket_liquidPlastic"
            }
        }
    ]
}
